rrplugins/README.txt
rrplugins/__init__.py
rrplugins/add_noise_example.py
rrplugins/auto2000_example1.py
rrplugins/auto2000_example2.py
rrplugins/chi_squared_example.py
rrplugins/hello_roadrunner_example.py
rrplugins/telAuto2000.py
rrplugins/telLevenbergMarquardt.py
rrplugins/telMonteCarlo.py
rrplugins/telNelderMead.py
rrplugins/telplugins.py
rrplugins/telplugins_c_api.py
rrplugins/libs/libroadrunner_c_api.dylib
rrplugins/libs/libtel_add_noise.so
rrplugins/libs/libtel_auto2000.so
rrplugins/libs/libtel_chisquare.so
rrplugins/libs/libtel_hello.so
rrplugins/libs/libtel_levenberg_marquardt.so
rrplugins/libs/libtel_monte_carlo_bs.so
rrplugins/libs/libtel_nelder_mead.so
rrplugins/libs/libtel_test_model.so
rrplugins/libs/telplugins_c_api.dylib
rrplugins/libs/telplugins_common.dylib
rrplugins/libs/telplugins_math.dylib
rrplugins-2.9.0.dist-info/licenses/AUTHORS.txt
rrplugins-2.9.0.dist-info/licenses/LICENSE.txt
rrplugins-2.9.0.dist-info/licenses/NOTICE.txt
rrplugins-2.9.0.dist-info/METADATA
rrplugins-2.9.0.dist-info/WHEEL
rrplugins-2.9.0.dist-info/top_level.txt
rrplugins-2.9.0.dist-info/RECORD
