Metadata-Version: 2.4
Name: rrplugins
Version: 2.9.0
Summary: rrplugins: Plugins to extend libroadrunner.
Home-page: http://libroadrunner.org
Author: Debashish Roy, M Totte Karlsson, J Kyle Medley, Herbert Sauro
Author-email: tellurium-discuss@u.washington.edu
Classifier: Intended Audience :: Science/Research
Classifier: Operating System :: MacOS :: MacOS X
Classifier: Operating System :: Microsoft :: Windows
Classifier: Operating System :: POSIX
Classifier: Programming Language :: C++
License-File: LICENSE.txt
License-File: NOTICE.txt
License-File: AUTHORS.txt
Requires-Dist: numpy>=2.4
Requires-Dist: matplotlib>=3
Dynamic: author
Dynamic: author-email
Dynamic: classifier
Dynamic: home-page
Dynamic: license-file
Dynamic: requires-dist
Dynamic: summary
